rusta_crawler/.gitignore
rusta_crawler/__init__.py
rusta_crawler/items.py
rusta_crawler/middlewares.py
rusta_crawler/pipelines.py
rusta_crawler/requirements.txt
rusta_crawler/scrapy.cfg
rusta_crawler/settings.py
rusta_crawler/files/constants.py
rusta_crawler/spiders/__init__.py
rusta_crawler/spiders/rusta_spider.py
rusta_crawler/sql/all_active_articles_de.sql
rusta_crawler/sql/all_active_articles_fi.sql
rusta_crawler/sql/all_active_articles_no.sql
rusta_crawler/sql/all_active_articles_se.sql
rusta_crawler/sql/campaign_of_the_week.sql
rusta_crawler/sql/package_price.sql
rusta_crawler/sql/rolling_campaigns.sql
rusta_crawler/tools/__init__.py
rusta_crawler/tools/logger.py
rusta_crawler-0.1.6.dist-info/METADATA
rusta_crawler-0.1.6.dist-info/WHEEL
rusta_crawler-0.1.6.dist-info/licenses/LICENSE
rusta_crawler-0.1.6.dist-info/RECORD
