Metadata-Version: 2.4
Name: rusta-crawler
Version: 0.1.6
Author-email: David Momeni <dav.momeni@gmail.com>
License-File: LICENSE
Classifier: License :: OSI Approved :: MIT License
Classifier: Operating System :: OS Independent
Classifier: Programming Language :: Python :: 3
Requires-Python: >=3.8
Requires-Dist: rusta-tools
Requires-Dist: scrapy
Requires-Dist: snowflake-connector-python
